pybuilder_integration/__init__.py
pybuilder_integration/artifact_manager.py
pybuilder_integration/cloudwatchlogs_utility.py
pybuilder_integration/directory_utility.py
pybuilder_integration/exec_utility.py
pybuilder_integration/properties.py
pybuilder_integration/tasks.py
pybuilder_integration/tool_utility.py
pybuilder_integration-102.dist-info/METADATA
pybuilder_integration-102.dist-info/WHEEL
pybuilder_integration-102.dist-info/namespace_packages.txt
pybuilder_integration-102.dist-info/top_level.txt
pybuilder_integration-102.dist-info/zip-safe
pybuilder_integration-102.dist-info/RECORD
