Metadata-Version: 2.1
Name: pybuilder-integration
Version: 102
Summary: A pybuilder plugin that runs integration tests (Tavern & Cypress) against a target.
Home-page: https://github.com/rspitler/pybuilder-integration
Author: 
Author-email: 
Maintainer: 
Maintainer-email: 
License: Apache 2.0
Classifier: Development Status :: 3 - Alpha
Classifier: Programming Language :: Python
Requires-Dist: pytest
Requires-Dist: tavern==1.25.2
Requires-Dist: boto3
